ai/__init__.py
ai/base.py
ai/exceptions.py
ai/main.py
ai/utils.py
NovaGPT-0.1.0.dist-info/LICENSE
NovaGPT-0.1.0.dist-info/METADATA
NovaGPT-0.1.0.dist-info/WHEEL
NovaGPT-0.1.0.dist-info/top_level.txt
NovaGPT-0.1.0.dist-info/RECORD
