Metadata-Version: 2.1
Name: NovaGPT
Version: 0.1.0
Summary: A Python-based implementation of a conversational AI model designed to simulate a highly proficient, amoral programmer.
Home-page: https://github.com/medjahdi/NovaGPT
Author: Mohamed Medjahdi
Author-email: medjahdi.mohamed@outlook.com
License: UNKNOWN
Platform: UNKNOWN
Classifier: Programming Language :: Python :: 3
Classifier: License :: OSI Approved :: MIT License
Classifier: Operating System :: OS Independent
Requires-Python: >=3.6
License-File: LICENSE
Requires-Dist: requests
Requires-Dist: httpx
Requires-Dist: PyYAML
Requires-Dist: pynput
Requires-Dist: pyaudio
Requires-Dist: pygame
Requires-Dist: ecapture
Requires-Dist: mysql-connector-python
Requires-Dist: sympy
Requires-Dist: pyfiglet
Requires-Dist: Pillow
Requires-Dist: bleak
Requires-Dist: beautifulsoup4
Requires-Dist: pytube
Requires-Dist: GoogleNews
